{
  "frames": {
    "Token2.png": {
      "frame": {
        "x": 0,
        "y": 0,
        "w": 95,
        "h": 95
      },
      "rotated": false,
      "trimmed": false,
      "spriteSourceSize": {
        "x": 0,
        "y": 0,
        "w": 95,
        "h": 95
      },
      "sourceSize": {
        "w": 95,
        "h": 95
      },
      "pivot": {
        "x": 0.5,
        "y": 0.5
      }
    },
    "Token3.png": {
      "frame": {
        "x": 95,
        "y": 0,
        "w": 95,
        "h": 95
      },
      "rotated": false,
      "trimmed": false,
      "spriteSourceSize": {
        "x": 0,
        "y": 0,
        "w": 95,
        "h": 95
      },
      "sourceSize": {
        "w": 95,
        "h": 95
      },
      "pivot": {
        "x": 0.5,
        "y": 0.5
      }
    },
    "Token4.png": {
      "frame": {
        "x": 190,
        "y": 0,
        "w": 95,
        "h": 95
      },
      "rotated": false,
      "trimmed": false,
      "spriteSourceSize": {
        "x": 0,
        "y": 0,
        "w": 95,
        "h": 95
      },
      "sourceSize": {
        "w": 95,
        "h": 95
      },
      "pivot": {
        "x": 0.5,
        "y": 0.5
      }
    },
    "Token5.png": {
      "frame": {
        "x": 285,
        "y": 0,
        "w": 95,
        "h": 95
      },
      "rotated": false,
      "trimmed": false,
      "spriteSourceSize": {
        "x": 0,
        "y": 0,
        "w": 95,
        "h": 95
      },
      "sourceSize": {
        "w": 95,
        "h": 95
      },
      "pivot": {
        "x": 0.5,
        "y": 0.5
      }
    }
  },
  "meta": {
    "app": "http://free-tex-packer.com",
    "version": "0.6.6",
    "image": "Tokens.png",
    "format": "RGBA8888",
    "size": {
      "w": 380,
      "h": 95
    },
    "scale": 1
  }
}